google_sheets_lib/__init__.py
google_sheets_lib/__version__.py
google_sheets_lib-0.4.dist-info/LICENSE.txt
google_sheets_lib-0.4.dist-info/METADATA
google_sheets_lib-0.4.dist-info/WHEEL
google_sheets_lib-0.4.dist-info/top_level.txt
google_sheets_lib-0.4.dist-info/RECORD
